django_prodserver/__init__.py
django_prodserver/apps.py
django_prodserver/backends/__init__.py
django_prodserver/backends/base.py
django_prodserver/backends/gunicorn.py
django_prodserver/backends/uvicorn.py
django_prodserver/backends/waitress.py
django_prodserver/management/__init__.py
django_prodserver/management/commands/__init__.py
django_prodserver/management/commands/devserver.py
django_prodserver/management/commands/prodserver.py
django_prodserver/migrations/__init__.py
django_prodserver/models.py
django_prodserver/tests.py
django_prodserver/utils.py
django_prodserver-2024.3.2.dist-info/LICENSE
django_prodserver-2024.3.2.dist-info/METADATA
django_prodserver-2024.3.2.dist-info/WHEEL
django_prodserver-2024.3.2.dist-info/RECORD
