Metadata-Version: 2.1
Name: django-prodserver
Version: 2024.3.2
Summary: A mangement command to provide a manage.py interface to production wsgi/asgi servers
Home-page: https://github.com/nanorepublica/django-prodserver
License: MIT
Author: Andrew Miller
Author-email: info@akmiller.co.uk
Requires-Python: >=3.9,<4.0
Classifier: Development Status :: 1 - Planning
Classifier: Environment :: Web Environment
Classifier: Framework :: Django
Classifier: Framework :: Django :: 3.2
Classifier: Framework :: Django :: 4.0
Classifier: Framework :: Django :: 4.1
Classifier: Framework :: Django :: 4.2
Classifier: License :: OSI Approved :: MIT License
Classifier: Programming Language :: Python :: 3
Classifier: Programming Language :: Python :: 3.9
Classifier: Programming Language :: Python :: 3.10
Classifier: Programming Language :: Python :: 3.11
Requires-Dist: click (>=8.0.1)
Requires-Dist: django (>=3.2)
Requires-Dist: django-click (>=2.3.0,<3.0.0)
Requires-Dist: gunicorn (>=21.2.0,<22.0.0)
Requires-Dist: uvicorn (>=0.27.1,<0.28.0)
Requires-Dist: waitress (>=3.0.0,<4.0.0)
Project-URL: Changelog, https://github.com/nanorepublica/django-prodserver/releases
Project-URL: Documentation, https://django-prodserver.readthedocs.io
Project-URL: Repository, https://github.com/nanorepublica/django-prodserver
